jinja2_git.py
jinja2_git-1.4.0.dist-info/LICENSE
jinja2_git-1.4.0.dist-info/METADATA
jinja2_git-1.4.0.dist-info/WHEEL
jinja2_git-1.4.0.dist-info/RECORD
