Metadata-Version: 2.1
Name: jinja2-git
Version: 1.4.0
Summary: Jinja2 extension to handle git-specific things
Home-page: https://github.com/wemake-services/jinja2-git
License: MIT
Keywords: jinja2,jinja2-extension,jinja2-plugin,git
Author: Nikita Sobolev
Author-email: mail@sobolenv.me
Requires-Python: >=3.9,<4.0
Classifier: Development Status :: 5 - Production/Stable
Classifier: Environment :: Console
Classifier: Intended Audience :: Developers
Classifier: License :: OSI Approved :: MIT License
Classifier: Operating System :: OS Independent
Classifier: Programming Language :: Python :: 3
Classifier: Programming Language :: Python :: 3.9
Classifier: Programming Language :: Python :: 3.10
Classifier: Programming Language :: Python :: 3.11
Classifier: Programming Language :: Python :: 3.12
Classifier: Topic :: Software Development :: Libraries :: Python Modules
Requires-Dist: jinja2 (>=2.10,<4.0)
Project-URL: Funding, https://github.com/sponsors/wemake-services
Project-URL: Repository, https://github.com/wemake-services/jinja2-git
